emotionsinai/__init__.py
emotionsinai/base_llm.py
emotionsinai/emotion_services.py
emotionsinai/internal_profile.py
emotionsinai/ollama_provider.py
emotionsinai/openai_provider.py
emotionsinai/reflection.py
emotionsinai/reponse.py
emotionsinai/response_split.py
emotionsinai/user_profile.py
emotionsinai/writing_style.py
emotionsinai-0.1.1.dist-info/licenses/LICENSE
emotionsinai-0.1.1.dist-info/METADATA
emotionsinai-0.1.1.dist-info/WHEEL
emotionsinai-0.1.1.dist-info/top_level.txt
emotionsinai-0.1.1.dist-info/RECORD
