Metadata-Version: 2.4
Name: emotionsinai
Version: 0.1.1
Summary: At Emotionsin.ai, we believe that effective collaboration between AI Agents and humans goes beyond technical expertise. Human interaction is built on social, emotional, and cultural foundations. By enhancing AI Agents with advanced emotional, social, and cultural understanding, we aim to create technology that integrates seamlessly into human contexts, delivering more personal, empathic, and impactful results.
Author-email: Gerrit Knippschild <gerritknippschild@gmail.com>
Keywords: aiagents,llm,emotions,empathy
Classifier: Programming Language :: Python :: 3
License-File: LICENSE
Dynamic: license-file
